core/__init__.py
core/admin.py
core/apps.py
core/models.py
core/tests.py
core/urls.py
core/views.py
core/migrations/__init__.py
nfckey/__init__.py
nfckey/settings.py
nfckey/urls.py
nfckey/wsgi.py
NFC_Key-0.1.0.dist-info/LICENSE
NFC_Key-0.1.0.dist-info/METADATA
NFC_Key-0.1.0.dist-info/WHEEL
NFC_Key-0.1.0.dist-info/top_level.txt
NFC_Key-0.1.0.dist-info/RECORD
