Metadata-Version: 2.1
Name: NFC-Key
Version: 0.1.0
Summary: NFC Key project
Home-page: https://changeme.com
Author: Pavel Isupov
Author-email: pavel.isupov.nz@gmail.com
License: LICENSE
Keywords: NFC
Platform: UNKNOWN
Requires-Python: >=3.6
